odoo10_addon_ovh_sms_client-10.0.1.0.1-py2.7-nspkg.pth
odoo/addons/ovh_sms_client/README.rst
odoo/addons/ovh_sms_client/__init__.py
odoo/addons/ovh_sms_client/__manifest__.py
odoo/addons/ovh_sms_client/data/keychain.xml
odoo/addons/ovh_sms_client/i18n/ar.po
odoo/addons/ovh_sms_client/i18n/ca.po
odoo/addons/ovh_sms_client/i18n/es.po
odoo/addons/ovh_sms_client/i18n/fr.po
odoo/addons/ovh_sms_client/models/__init__.py
odoo/addons/ovh_sms_client/models/keychain.py
odoo/addons/ovh_sms_client/models/sms_gateway.py
odoo10_addon_ovh_sms_client-10.0.1.0.1.dist-info/DESCRIPTION.rst
odoo10_addon_ovh_sms_client-10.0.1.0.1.dist-info/METADATA
odoo10_addon_ovh_sms_client-10.0.1.0.1.dist-info/RECORD
odoo10_addon_ovh_sms_client-10.0.1.0.1.dist-info/WHEEL
odoo10_addon_ovh_sms_client-10.0.1.0.1.dist-info/metadata.json
odoo10_addon_ovh_sms_client-10.0.1.0.1.dist-info/namespace_packages.txt
odoo10_addon_ovh_sms_client-10.0.1.0.1.dist-info/top_level.txt
