Metadata-Version: 2.0
Name: odoo10-addon-ovh-sms-client
Version: 10.0.1.0.1
Summary: OVH SMS Client
Home-page: http://julius.fr
Author: Julius Network Solutions,SYLEAM,Odoo Community Association (OCA),Akretion
Author-email: support@odoo-community.org
License: AGPL-3
Platform: UNKNOWN
Classifier: Programming Language :: Python
Classifier: Framework :: Odoo
Classifier: License :: OSI Approved :: GNU Affero General Public License v3
Requires-Python: ~=2.7
Requires-Dist: odoo (<10.1dev,>=10.0)
Requires-Dist: odoo10-addon-base-sms-client
Requires-Dist: odoo10-addon-base-suspend-security
Requires-Dist: odoo10-addon-keychain
